phastSim/__init__.py
phastSim/parsimony_pb2.py
phastSim/phastSim.py
phastSim/example/MN908947.3.fasta
phastSim/example/__init__.py
phastSim/example/exampleTree.tree
phastSim/example/example_sarscov2_tree.newick
phastSim-0.0.6.data/scripts/phastSim
phastSim-0.0.6.dist-info/LICENSE
phastSim-0.0.6.dist-info/METADATA
phastSim-0.0.6.dist-info/WHEEL
phastSim-0.0.6.dist-info/top_level.txt
phastSim-0.0.6.dist-info/RECORD
