Metadata-Version: 2.1
Name: phastSim
Version: 0.0.6
Summary: Fast sequence evolution simulation for SARS-CoV-2 phylogenies and other genomic epidemiological datasets
Home-page: https://github.com/NicolaDM/phastSim
Author: Nicola De Maio
Author-email: demaio@ebi.ac.uk
Classifier: Programming Language :: Python :: 3
Classifier: Operating System :: OS Independent
Requires-Python: >=3.6
License-File: LICENSE
Requires-Dist: numpy
Requires-Dist: ete3
Requires-Dist: Biopython
Requires-Dist: argparse
Requires-Dist: six
Requires-Dist: importlib-resources
Requires-Dist: google
Requires-Dist: protobuf (==3.20.*)
